azure/servicefabric/__init__.py
azure/servicefabric/credentials.py
azure/servicefabric/exceptions.py
azure/servicefabric/service_fabric_client_ap_is.py
azure/servicefabric/version.py
azure/servicefabric/models/__init__.py
azure/servicefabric/models/aad_metadata.py
azure/servicefabric/models/aad_metadata_object.py
azure/servicefabric/models/application_capacity_description.py
azure/servicefabric/models/application_description.py
azure/servicefabric/models/application_health.py
azure/servicefabric/models/application_health_evaluation.py
azure/servicefabric/models/application_health_policies.py
azure/servicefabric/models/application_health_policy.py
azure/servicefabric/models/application_health_policy_map_item.py
azure/servicefabric/models/application_health_state.py
azure/servicefabric/models/application_health_state_chunk.py
azure/servicefabric/models/application_health_state_chunk_list.py
azure/servicefabric/models/application_health_state_filter.py
azure/servicefabric/models/application_info.py
azure/servicefabric/models/application_load_info.py
azure/servicefabric/models/application_metric_description.py
azure/servicefabric/models/application_name_info.py
azure/servicefabric/models/application_parameter.py
azure/servicefabric/models/application_type_applications_health_evaluation.py
azure/servicefabric/models/application_type_health_policy_map_item.py
azure/servicefabric/models/application_type_image_store_path.py
azure/servicefabric/models/application_type_image_store_version.py
azure/servicefabric/models/application_type_info.py
azure/servicefabric/models/application_type_manifest.py
azure/servicefabric/models/application_upgrade_description.py
azure/servicefabric/models/application_upgrade_progress_info.py
azure/servicefabric/models/application_upgrade_update_description.py
azure/servicefabric/models/applications_health_evaluation.py
azure/servicefabric/models/chaos_context.py
sfctl_azure_servicefabric-6.0.0rc1.dist-info/DESCRIPTION.rst
sfctl_azure_servicefabric-6.0.0rc1.dist-info/METADATA
sfctl_azure_servicefabric-6.0.0rc1.dist-info/RECORD
sfctl_azure_servicefabric-6.0.0rc1.dist-info/WHEEL
sfctl_azure_servicefabric-6.0.0rc1.dist-info/metadata.json
sfctl_azure_servicefabric-6.0.0rc1.dist-info/top_level.txt
