Metadata-Version: 2.0
Name: sfctl-azure-servicefabric
Version: 6.0.0rc1
Summary: Microsoft Azure ServiceFabric Client Library for Python
Home-page: https://github.com/Azure/azure-sdk-for-python
Author: Microsoft Corporation
Author-email: ptvshelp@microsoft.com
License: MIT License
Platform: UNKNOWN
Classifier: Development Status :: 4 - Beta
Classifier: Programming Language :: Python
Classifier: Programming Language :: Python :: 2
Classifier: Programming Language :: Python :: 2.7
Classifier: Programming Language :: Python :: 3
Classifier: Programming Language :: Python :: 3.3
Classifier: Programming Language :: Python :: 3.4
Classifier: Programming Language :: Python :: 3.5
Classifier: Programming Language :: Python :: 3.6
Classifier: License :: OSI Approved :: MIT License
Requires-Dist: azure-common (~=1.1.5)
Requires-Dist: azure-nspkg (>=2.0.0)
Requires-Dist: msrestazure (~=0.4.7)
